MANIFEST.in
README.txt
setup.py
django_photologue_praekelt.egg-info/PKG-INFO
django_photologue_praekelt.egg-info/SOURCES.txt
django_photologue_praekelt.egg-info/dependency_links.txt
django_photologue_praekelt.egg-info/not-zip-safe
django_photologue_praekelt.egg-info/top_level.txt
photologue/__init__.py
photologue/admin.py
photologue/models.py
photologue/tests.py
photologue/urls.py
photologue/locale/pl/LC_MESSAGES/django.mo
photologue/locale/pl/LC_MESSAGES/django.po
photologue/management/__init__.py
photologue/management/commands/__init__.py
photologue/management/commands/plcache.py
photologue/management/commands/plcreatesize.py
photologue/management/commands/plflush.py
photologue/management/commands/plinit.py
photologue/res/sample.jpg
photologue/res/test spaced file.jpg
photologue/res/test_landscape.jpg
photologue/res/test_nonsense.jpg
photologue/res/test_portrait.jpg
photologue/res/test_square.jpg
photologue/res/test_unicode_®.jpg
photologue/templates/photologue/gallery_archive.html
photologue/templates/photologue/gallery_archive_day.html
photologue/templates/photologue/gallery_archive_month.html
photologue/templates/photologue/gallery_archive_year.html
photologue/templates/photologue/gallery_detail.html
photologue/templates/photologue/gallery_list.html
photologue/templates/photologue/photo_archive.html
photologue/templates/photologue/photo_archive_day.html
photologue/templates/photologue/photo_archive_month.html
photologue/templates/photologue/photo_archive_year.html
photologue/templates/photologue/photo_detail.html
photologue/templates/photologue/photo_list.html
photologue/templates/photologue/root.html
photologue/templates/photologue/tags/next_in_gallery.html
photologue/templates/photologue/tags/prev_in_gallery.html
photologue/templatetags/__init__.py
photologue/templatetags/photologue_tags.py
photologue/utils/EXIF.py
photologue/utils/__init__.py
photologue/utils/reflection.py
photologue/utils/watermark.py