Metadata-Version: 1.1
Name: django-photologue-praekelt
Version: 2.10.3
Summary: Powerful image management for the Django web framework. Praekelt fork.
Home-page: https://github.com/praekelt/django-photologue/
Author: Justin Driscoll
Author-email: hedley@praekelt.com
License: UNKNOWN
Platform: UNKNOWN
Classifier: Development Status :: 5 - Production/Stable
Classifier: Environment :: Web Environment
Classifier: Framework :: Django
Classifier: Intended Audience :: Developers
Classifier: License :: OSI Approved :: BSD License
Classifier: Operating System :: OS Independent
Classifier: Programming Language :: Python
Classifier: Topic :: Utilities
